{"type":"FeatureCollection","features":[{"type":"Feature","properties":{"name":"Sunnansj\u00f6 g\u00e5rd","id":2872,"link":"https:\/\/www.fjardhundraland.se\/plats\/sunnansjo-gard\/","marker-color":"#f00","marker-size":"small"},"geometry":{"type":"Point","coordinates":[17.158667899999955,59.86214769999999]}}]}