{"type":"FeatureCollection","features":[{"type":"Feature","properties":{"name":"Skattmans\u00f6backen","id":1602,"link":"https:\/\/www.fjardhundraland.se\/plats\/skattmansobacken\/","marker-color":"#f00","marker-size":"small"},"geometry":{"type":"Point","coordinates":[17.060587406158447,59.831839650757864]}},{"type":"Feature","properties":{"name":"\u00c4s puss","id":3687,"link":"https:\/\/www.fjardhundraland.se\/plats\/as-puss\/","marker-color":"#f00","marker-size":"small"},"geometry":{"type":"Point","coordinates":[17.096614837646484,59.715090425871665]}}]}