{"type":"FeatureCollection","features":[{"type":"Feature","properties":{"name":"H\u00e4rkeberga church","id":194,"link":"https:\/\/www.fjardhundraland.se\/en\/plats\/harkeberga-church\/","marker-color":"#f00","marker-size":"small"},"geometry":{"type":"Point","coordinates":[17.187799199999972,59.693034]}}]}