{"type":"FeatureCollection","features":[{"type":"Feature","properties":{"name":"Hornuddens tr\u00e4dg\u00e5rd","id":5833,"link":"https:\/\/www.fjardhundraland.se\/plats\/hornuddens-tradgard\/","marker-color":"#f00","marker-size":"small"},"geometry":{"type":"Point","coordinates":[17.03254222869873,59.43944594258526]}},{"type":"Feature","properties":{"name":"Kvarnnibble Butik och Musteri","id":4900,"link":"https:\/\/www.fjardhundraland.se\/plats\/kvarnnibble-butik-och-musteri\/","marker-color":"#f00","marker-size":"small"},"geometry":{"type":"Point","coordinates":[17.62539179999999,59.59924179999999]}}]}