{"type":"FeatureCollection","features":[{"type":"Feature","properties":{"name":"H\u00e4rkeberga kyrka","id":1745,"link":"https:\/\/www.fjardhundraland.se\/plats\/harkeberga-kyrka\/","marker-color":"#f00","marker-size":"small"},"geometry":{"type":"Point","coordinates":[17.18783140182495,59.693044897644384]}}]}