{"type":"FeatureCollection","features":[{"type":"Feature","properties":{"name":"Meet the Moose at G\u00e5rdsj\u00f6","id":463,"link":"https:\/\/www.fjardhundraland.se\/en\/plats\/gardsjo-moose\/","marker-color":"#f00","marker-size":"small"},"geometry":{"type":"Point","coordinates":[16.9695699,59.9625935]}}]}