{"type":"FeatureCollection","features":[{"type":"Feature","properties":{"name":"Orresta Golf &#038; Konferens","id":5666,"link":"https:\/\/www.fjardhundraland.se\/en_us\/plats\/orresta-golf-konferens\/","marker-color":"#f00","marker-size":"small"},"geometry":{"type":"Point","coordinates":[16.839090103161766,59.66316063770292]}}]}