{"type":"FeatureCollection","features":[{"type":"Feature","properties":{"name":"Trolltrappan","id":2438,"link":"https:\/\/www.fjardhundraland.se\/plats\/trolltrappan\/","marker-color":"#f00","marker-size":"small"},"geometry":{"type":"Point","coordinates":[17.021641731262207,59.77928881798724]}}]}